{
  "slug": "typescript-basics-class-as-types",
  "title": "Классы как типы",
  "language": "javascript",
  "filesToOpen": [
    "solution.ts"
  ],
  "studentFiles": [
    "solution.ts"
  ],
  "readme": "## solution.ts\n\nРеализуйте класс `File`, в конструктор которого передается имя файла и размер в байтах или другой файл. Внутри класса определите метод `toString()`, который должен вернуть форматированную строку в формате `(copy) <file-name> (<size> bytes)`. `(copy)` должно выводиться только в случае, если файл является копией другого файла.\n\n```typescript\nconst file1 = new File({ name: 'open-world.jpeg', size: 1000 });\nconsole.log(`${file1}`); // open-world.jpeg (1000 bytes)\n\nconst file2 = new File(file1);\nconsole.log(`${file2}`); // (copy) open-world.jpeg (1000 bytes)\n\nconst file3 = new File(file2);\nconsole.log(`${file3}`); // (copy) open-world.jpeg (1000 bytes)\n```\n\n### Подсказки\n\n* Проверку на копию можно сделать через проверку типа переданного в конструктор объекта\n",
  "hexlet": {
    "courseSlug": "typescript-advanced",
    "courseName": "Продвинутый Typescript",
    "lessonSlug": "class-as-types",
    "lessonName": "Классы как типы",
    "exerciseSlug": "typescript_basics_class_as_types",
    "sourceUrl": "https://ru.hexlet.io/courses/typescript-advanced/lessons/class-as-types/exercise_unit"
  }
}
