{
  "slug": "js-frontend-architecture-shape-of-state",
  "title": "Нормализация данных",
  "language": "javascript",
  "filesToOpen": [
    "src/application.js"
  ],
  "studentFiles": [
    "src/application.js"
  ],
  "readme": "_Эта задача не сложная алгоритмически, но довольно объемная. На решение потребуется время и это хорошая прокачка_\n\nВ этой задаче вам предстоит сделать список задач похожий на [Reminders из MacOS](https://bit.ly/38GX3wI). Reminder позволяет планировать задачи и создавать списки задач.\n\n![Пример работы](assets/example.gif)\n\nПо умолчанию, в нашей реализации сразу должен быть создан список General. Начальный HTML доступен в _public/index.html_. После инициализации js он становится таким (туда добавляется General):\n\n```html\n<div class=\"row\">\n  <div class=\"col\">\n    <h3>Lists</h3>\n    <form class=\"d-flex mb-2\" data-container=\"new-list-form\">\n      <label for=\"new-list-name\" class=\"visually-hidden\">New list name</label>\n      <input\n        type=\"text\"\n        id=\"new-list-name\"\n        class=\"form-control me-2\"\n        name=\"name\"\n        required\n      />\n      <input type=\"submit\" class=\"btn btn-primary\" value=\"Add List\" />\n    </form>\n    <div data-container=\"lists\">\n      <ul>\n        <li><b>General</b></li>\n      </ul>\n    </div>\n  </div>\n  <div class=\"col\">\n    <h3>Tasks</h3>\n    <form class=\"d-flex mb-2\" data-container=\"new-task-form\">\n      <label for=\"new-task-name\" class=\"visually-hidden\">New task name</label>\n      <input\n        type=\"text\"\n        id=\"new-task-name\"\n        class=\"form-control me-2\"\n        name=\"name\"\n        required\n      />\n      <input type=\"submit\" class=\"btn btn-primary\" value=\"Add Task\" />\n    </form>\n    <div data-container=\"tasks\"></div>\n  </div>\n</div>\n```\n\nПосле добавления первой задачи в список General:\n\n```html\n<div class=\"row\">\n  <div class=\"col\">\n    <h3>Lists</h3>\n    <form class=\"d-flex mb-2\" data-container=\"new-list-form\">\n      <label for=\"new-list-name\" class=\"visually-hidden\">New list name</label>\n      <input\n        type=\"text\"\n        id=\"new-list-name\"\n        class=\"form-control me-2\"\n        name=\"name\"\n        required\n      />\n      <input type=\"submit\" class=\"btn btn-primary\" value=\"Add List\" />\n    </form>\n    <div data-container=\"lists\">\n      <ul>\n        <li><b>General</b></li>\n      </ul>\n    </div>\n  </div>\n  <div class=\"col\">\n    <h3>Tasks</h3>\n    <form class=\"d-flex mb-2\" data-container=\"new-task-form\">\n      <label for=\"new-task-name\" class=\"visually-hidden\">New task name</label>\n      <input\n        type=\"text\"\n        id=\"new-task-name\"\n        class=\"form-control me-2\"\n        name=\"name\"\n        required\n      />\n      <input type=\"submit\" class=\"btn btn-primary\" value=\"Add Task\" />\n    </form>\n    <div data-container=\"tasks\">\n      <ul>\n        <li>My First Task</li>\n      </ul>\n    </div>\n  </div>\n</div>\n```\n\nПосле создания нового списка (но до переключения на него):\n\n```html\n<div class=\"row\">\n  <div class=\"col\">\n    <h3>Lists</h3>\n    <form class=\"d-flex mb-2\" data-container=\"new-list-form\">\n      <label for=\"new-list-name\" class=\"visually-hidden\">New list name</label>\n      <input\n        type=\"text\"\n        id=\"new-list-name\"\n        class=\"form-control me-2\"\n        name=\"name\"\n        required\n      />\n      <input type=\"submit\" class=\"btn btn-primary\" value=\"Add List\" />\n    </form>\n    <div data-container=\"lists\">\n      <ul>\n        <li><b>General</b></li>\n        <li><a href=\"#random\">Random</a></li>\n      </ul>\n    </div>\n  </div>\n  <div class=\"col\">\n    <h3>Tasks</h3>\n    <form class=\"d-flex mb-2\" data-container=\"new-task-form\">\n      <label for=\"new-task-name\" class=\"visually-hidden\">New task name</label>\n      <input\n        type=\"text\"\n        id=\"new-task-name\"\n        class=\"form-control me-2\"\n        name=\"name\"\n        required\n      />\n      <input type=\"submit\" class=\"btn btn-primary\" value=\"Add Task\" />\n    </form>\n    <div data-container=\"tasks\">\n      <ul>\n        <li>My First Task</li>\n      </ul>\n    </div>\n  </div>\n</div>\n```\n\nПосле переключения на список Random (клик по имени):\n\n```html\n<div class=\"row\">\n  <div class=\"col\">\n    <h3>Lists</h3>\n    <form class=\"d-flex mb-2\" data-container=\"new-list-form\">\n      <label for=\"new-list-name\" class=\"visually-hidden\">New list name</label>\n      <input\n        type=\"text\"\n        id=\"new-list-name\"\n        class=\"form-control me-2\"\n        name=\"name\"\n        required\n      />\n      <input type=\"submit\" class=\"btn btn-primary\" value=\"Add List\" />\n    </form>\n    <div data-container=\"lists\">\n      <ul>\n        <li><a href=\"#general\">General</a></li>\n        <li><b>Random</b></li>\n      </ul>\n    </div>\n  </div>\n  <div class=\"col\">\n    <h3>Tasks</h3>\n    <form class=\"d-flex mb-2\" data-container=\"new-task-form\">\n      <label for=\"new-task-name\" class=\"visually-hidden\">New task name</label>\n      <input\n        type=\"text\"\n        id=\"new-task-name\"\n        class=\"form-control me-2\"\n        name=\"name\"\n        required\n      />\n      <input type=\"submit\" class=\"btn btn-primary\" value=\"Add Task\" />\n    </form>\n    <div data-container=\"tasks\"></div>\n  </div>\n</div>\n```\n\nСписки должны иметь уникальные имена. Добавление списка с уже существующим именем не должно производить никакого эффекта.\n\n### src/application.js\n\nЭкспортируйте функцию по умолчанию, которая реализует всю необходимую логику.\n",
  "hexlet": {
    "courseSlug": "js-frontend-architecture",
    "courseName": "JS: Архитектура фронтенда",
    "lessonSlug": "shape-of-state",
    "lessonName": "Нормализация данных",
    "exerciseSlug": "js_frontend_architecture_shape_of_state_exercise",
    "sourceUrl": "https://ru.hexlet.io/courses/js-frontend-architecture/lessons/shape-of-state/exercise_unit"
  }
}
